f1_telemetry/__init__.py
f1_telemetry/__main__.py
f1_telemetry/collector.py
f1_telemetry/live.py
f1_telemetry/model.py
f1_telemetry/report.py
f1_telemetry/server.py
f1_telemetry/storage.py
f1_telemetry/view.py
f1_telemetry/webapp/art/Formula1-Regular.ttf
f1_telemetry/webapp/art/bg.jpg
f1_telemetry/webapp/art/car.svg
f1_telemetry/webapp/index.html
f1_telemetry/webapp/live.html
f1_telemetry/webapp/live.js
f1_telemetry/webapp/plots.js
f1_telemetry/webapp/queries.js
f1_telemetry/webapp/style.css
f1_telemetry/webapp/trace.js
f1_telemetry/webapp/utils.js
f1_telemetry/webapp/view.js
f1_telemetry-2025.3.3.dist-info/METADATA
f1_telemetry-2025.3.3.dist-info/WHEEL
f1_telemetry-2025.3.3.dist-info/entry_points.txt
f1_telemetry-2025.3.3.dist-info/RECORD
