Metadata-Version: 2.3
Name: f1-telemetry
Version: 2025.3.3
Summary: F1 telemetry data collection and visualisation
License: MIT
Author: Gabriele N. Tornetta
Author-email: phoenix1987@gmail.com
Requires-Python: >=3.8,<4.0
Classifier: Intended Audience :: Developers
Classifier: License :: OSI Approved :: MIT License
Classifier: Programming Language :: Python :: 3
Classifier: Programming Language :: Python :: 3.8
Classifier: Programming Language :: Python :: 3.9
Classifier: Programming Language :: Python :: 3.10
Classifier: Programming Language :: Python :: 3.11
Classifier: Programming Language :: Python :: 3.12
Classifier: Programming Language :: Python :: 3.13
Requires-Dist: f1-packets (>=2025.1.0,<2026.0.0)
Requires-Dist: influxdb-client (>=1.30.0,<2.0.0)
Requires-Dist: pyttsx3 (==2.71)
Requires-Dist: websockets (>=10.3,<11.0)
Project-URL: Repository, https://github.com/P403n1x87/f1-telemetry
Project-URL: issues, https://github.com/P403n1x87/f1-telemetry/issues
